macrocycle-0.2.0.dist-info/licenses/LICENSE
macros/__init__.py
macros/cli.py
macros/application/__init__.py
macros/application/container.py
macros/application/presenters/__init__.py
macros/application/presenters/formatters.py
macros/application/services/__init__.py
macros/application/services/batch_orchestrator.py
macros/application/services/preview_builder.py
macros/application/services/source_registry.py
macros/application/usecases/__init__.py
macros/application/usecases/batch_fix_work_items.py
macros/application/usecases/discover_work_items.py
macros/application/usecases/fix_work_item.py
macros/application/usecases/get_status.py
macros/application/usecases/init_repo.py
macros/application/usecases/list_macros.py
macros/application/usecases/preview_macro.py
macros/application/usecases/run_macro.py
macros/domain/__init__.py
macros/domain/exceptions.py
macros/domain/model/__init__.py
macros/domain/model/batch_result.py
macros/domain/model/cycle.py
macros/domain/model/cycle_info.py
macros/domain/model/macro.py
macros/domain/model/macro_preview.py
macros/domain/model/work_item.py
macros/domain/ports/__init__.py
macros/domain/ports/agent_port.py
macros/domain/ports/console_port.py
macros/domain/ports/cycle_store_port.py
macros/domain/ports/macro_registry_port.py
macros/domain/ports/source_config_port.py
macros/domain/ports/work_item_source_port.py
macros/domain/services/__init__.py
macros/domain/services/cycle_orchestrator.py
macros/domain/services/macro_validator.py
macros/domain/services/prompt_builder.py
macros/domain/services/template_renderer.py
macros/infrastructure/__init__.py
macros/infrastructure/config/__init__.py
macros/infrastructure/config/env_config.py
macros/infrastructure/persistence/__init__.py
macros/infrastructure/persistence/cycle_store.py
macros/infrastructure/persistence/macro_store.py
macros/infrastructure/persistence/defaults/__init__.py
macros/infrastructure/persistence/defaults/fix.json
macros/infrastructure/persistence/mappers/__init__.py
macrocycle-0.2.0.dist-info/METADATA
macrocycle-0.2.0.dist-info/WHEEL
macrocycle-0.2.0.dist-info/entry_points.txt
macrocycle-0.2.0.dist-info/top_level.txt
macrocycle-0.2.0.dist-info/RECORD
