Metadata-Version: 2.4
Name: macrocycle
Version: 0.2.0
Summary: Ritualized AI agent workflows - multi-pass prompt pipelines for Cursor and beyond
Author: Milan Pecov
License: MIT
Project-URL: Homepage, https://github.com/MilanPecov/macrocycle
Project-URL: Repository, https://github.com/MilanPecov/macrocycle
Keywords: ai,agent,cursor,workflow,automation,llm
Classifier: Development Status :: 3 - Alpha
Classifier: Intended Audience :: Developers
Classifier: License :: OSI Approved :: MIT License
Classifier: Programming Language :: Python :: 3
Classifier: Programming Language :: Python :: 3.10
Classifier: Programming Language :: Python :: 3.11
Classifier: Programming Language :: Python :: 3.12
Classifier: Topic :: Software Development :: Libraries
Requires-Python: >=3.10
License-File: LICENSE
Requires-Dist: typer>=0.12.0
Requires-Dist: pydantic>=2.0.0
Requires-Dist: rich>=13.0.0
Requires-Dist: jinja2>=3.1.0
Requires-Dist: textual>=0.50.0
Provides-Extra: test
Requires-Dist: pytest>=8.0.0; extra == "test"
Provides-Extra: dev
Requires-Dist: pytest>=8.0.0; extra == "dev"
Requires-Dist: commitizen>=4.0.0; extra == "dev"
Dynamic: license-file
